BifacialSimu_src/BifacialSimu_main.py
BifacialSimu_src/GUI.py
BifacialSimu_src/__init__.py
BifacialSimu_src/_version.py
BifacialSimu_src/globals.py
BifacialSimu_src/BifacialSimu/__init__.py
BifacialSimu_src/BifacialSimu/Controller/BifacialSimu_simulationController.py
BifacialSimu_src/BifacialSimu/Controller/__init__.py
BifacialSimu_src/BifacialSimu/Controller/__pycache__/BifacialSimu_simulationController.cpython-39.pyc
BifacialSimu_src/BifacialSimu/Controller/__pycache__/__init__.cpython-39.pyc
BifacialSimu_src/BifacialSimu/Handler/BifacialSimu_calculationHandler.py
BifacialSimu_src/BifacialSimu/Handler/BifacialSimu_dataHandler.py
BifacialSimu_src/BifacialSimu/Handler/BifacialSimu_radiationHandler.py
BifacialSimu_src/BifacialSimu/Handler/BifacialSimu_spectralAlbedoHandler.py
BifacialSimu_src/BifacialSimu/Handler/BifacialSimu_spectralAlbedoHandler_1_row.py
BifacialSimu_src/BifacialSimu/Handler/__init__.py
BifacialSimu_src/BifacialSimu/Handler/__pycache__/BifacialSimu_calculationHandler.cpython-39.pyc
BifacialSimu_src/BifacialSimu/Handler/__pycache__/BifacialSimu_dataHandler.cpython-39.pyc
BifacialSimu_src/BifacialSimu/Handler/__pycache__/BifacialSimu_radiationHandler.cpython-39.pyc
BifacialSimu_src/BifacialSimu/Handler/__pycache__/BifacialSimu_spectralAlbedoHandler.cpython-39.pyc
BifacialSimu_src/BifacialSimu/Handler/__pycache__/BifacialSimu_spectralAlbedoHandler_1_row.cpython-39.pyc
BifacialSimu_src/BifacialSimu/Handler/__pycache__/__init__.cpython-39.pyc
BifacialSimu_src/BifacialSimu/__pycache__/__init__.cpython-39.pyc
BifacialSimu_src/Data_conversion/10minute_Flughafen.csv
BifacialSimu_src/Data_conversion/10minute_to_minute_radiation.py
BifacialSimu_src/Data_conversion/15minute_to_hourly_albedo.py
BifacialSimu_src/Data_conversion/Golden_Albedo_15Min.csv
BifacialSimu_src/Data_conversion/Measurement_Albedo.csv
BifacialSimu_src/Data_conversion/Measurement_GHI_DHI_DNI.csv
BifacialSimu_src/Data_conversion/hourly_Albedo.csv
BifacialSimu-1.2.0.dist-info/LICENSE
BifacialSimu-1.2.0.dist-info/METADATA
BifacialSimu-1.2.0.dist-info/WHEEL
BifacialSimu-1.2.0.dist-info/top_level.txt
BifacialSimu-1.2.0.dist-info/RECORD
