Metadata-Version: 2.1
Name: BifacialSimu
Version: 1.2.0
Summary: Holistic Simulation of large-scale Bifacial Photovoltaic Systems
Home-page: https://github.com/cire-thk/BifacialSimu
Author: Eva-Maria Grommes
Author-email: Eva-Maria.Grommes@th-koeln.de
Keywords: Bifacialsimu,bifacial simulation,energy yield of bifacial PV systems,albedo
Classifier: Programming Language :: Python
Classifier: Programming Language :: Python :: 3
Classifier: Programming Language :: Python :: 3.9
Classifier: Development Status :: 4 - Beta
License-File: LICENSE
Requires-Dist: pandas (==1.3.4)
Requires-Dist: ipython (==7.34.0)
Requires-Dist: matplotlib (==3.4.3)
Requires-Dist: numpy (==1.20.3)
Requires-Dist: Pillow (==9.1.1)
Requires-Dist: pvlib (==0.9.1)
Requires-Dist: python-dateutil (==2.8.2)
Requires-Dist: pytz (==2021.3)
Requires-Dist: requests (==2.28.1)
Requires-Dist: seaborn (==0.11.2)
Requires-Dist: Shapely (==1.8.2)
Requires-Dist: tqdm (==4.62.3)
Requires-Dist: bifacial-radiance (==0.4.1)
Requires-Dist: pyqt5 (==5.12.3)
Requires-Dist: pyqtwebengine (==5.12.1)
Requires-Dist: pvfactors (==1.5.2)
Requires-Dist: daal (==2021.4.0)
Requires-Dist: clyent (==1.2.1)
Requires-Dist: nbformat (==5.4.0)
Requires-Dist: ruamel.yaml (==0.17.21)
